interview/uart_transmitter/uart_transmitter.v
module uart_transmitter(
    input clk,
    input rst,
    input [7:0] data,
    input load,
    output wire tx
);
    reg[8:0] tx_queue = 9'b111111111;
    reg[4:0] transmit = 5'd9;
    reg tx_reg = 1'b1;
    assign tx = tx_reg;
    always @(negedge clk) tx_reg = (transmit > 0) ? tx_queue[0] : 1'b1;

    always @(posedge clk) begin
        if (rst) begin
            transmit <= 0;
            tx_queue <= 9'b111111111;
        end else if (load) begin
            transmit <= 9;
            tx_queue <= {data, 1'b0};
        end else if (transmit > 0) begin
            tx_queue <= {1'b1, tx_queue[8:1]};
            transmit <= transmit - 1;
        end
    end

endmodule

interview/uart_transmitter/uart_transmitter_tb.v
`timescale 1ns/1ns
`include "uart_transmitter.v"

module uart_transmitter_tb;
    reg clk, rst, load;
    reg[7:0] data;

    always @(*) #1 clk <= ~clk;


    wire tx;

    uart_transmitter dut(
        .clk(clk),
        .rst(rst),
        .load(load),
        .data(data),
        .tx(tx)
    );

    initial begin
        $dumpfile("uart_transmitter_tb.vcd");
        $dumpvars(0, uart_transmitter_tb);

        clk = 0;
        rst = 0;
        load = 0;

        @(posedge clk);
        rst <= 1;
        @(posedge clk);
        rst <= 0;
        @(posedge clk);

        @(negedge clk);
        load <= 1;
        data <= 8'b10101010;

        @(negedge clk);
        load <= 0;
        
        repeat(15) @(posedge clk);
        
        @(negedge clk);
        load <= 1;
        data <= 8'b01011100;

        @(negedge clk);
        load <= 0;
        
        repeat(15) @(posedge clk);

        $finish;

    end



endmodule

interview/uart_transmitter/uart_transmitter_tb.vcd
$date
	Fri Nov 03 23:51:02 2023
$end
$version
	Icarus Verilog
$end
$timescale
	1ns
$end
$scope module uart_transmitter_tb $end
$var wire 1 ! tx $end
$var reg 1 " clk $end
$var reg 8 # data [7:0] $end
$var reg 1 $ load $end
$var reg 1 % rst $end
$scope module dut $end
$var wire 1 " clk $end
$var wire 8 & data [7:0] $end
$var wire 1 $ load $end
$var wire 1 % rst $end
$var wire 1 ! tx $end
$var reg 5 ' transmit [4:0] $end
$var reg 9 ( tx_queue [8:0] $end
$var reg 1 ) tx_reg $end
$upscope $end
$upscope $end
$enddefinitions $end
$comment Show the parameter values. $end
$dumpall
$end
#0
$dumpvars
1)
b111111111 (
b1001 '
bx &
0%
0$
bx #
0"
1!
$end
#1
b1000 '
1%
1"
#2
0"
#3
0%
b0 '
1"
#4
0"
#5
1"
#6
b10101010 #
b10101010 &
1$
0"
#7
b101010100 (
b1001 '
1"
#8
0$
0!
0)
0"
#9
b1000 '
b110101010 (
1"
#10
0"
#11
b111 '
b111010101 (
1"
#12
1!
1)
0"
#13
b110 '
b111101010 (
1"
#14
0!
0)
0"
#15
b101 '
b111110101 (
1"
#16
1!
1)
0"
#17
b100 '
b111111010 (
1"
#18
0!
0)
0"
#19
b11 '
b111111101 (
1"
#20
1!
1)
0"
#21
b10 '
b111111110 (
1"
#22
0!
0)
0"
#23
b1 '
b111111111 (
1"
#24
1!
1)
0"
#25
b0 '
1"
#26
0"
#27
1"
#28
0"
#29
1"
#30
0"
#31
1"
#32
0"
#33
1"
#34
0"
#35
1"
#36
0"
#37
1"
#38
b1011100 #
b1011100 &
1$
0"
#39
b10111000 (
b1001 '
1"
#40
0$
0!
0)
0"
#41
b1000 '
b101011100 (
1"
#42
0"
#43
b111 '
b110101110 (
1"
#44
0"
#45
b110 '
b111010111 (
1"
#46
1!
1)
0"
#47
b101 '
b111101011 (
1"
#48
0"
#49
b100 '
b111110101 (
1"
#50
0"
#51
b11 '
b111111010 (
1"
#52
0!
0)
0"
#53
b10 '
b111111101 (
1"
#54
1!
1)
0"
#55
b1 '
b111111110 (
1"
#56
0!
0)
0"
#57
b0 '
b111111111 (
1"
#58
1!
1)
0"
