interview/traffic_light/traffic_light.v
module traffic_light(
    output reg[1:0] state,
    input clk
);

    parameter r2g = 7;
    parameter g2y = 10;
    parameter y2r = 4;

    reg[3:0] cur_time = 4'd0;

    parameter red = 2'b00;
    parameter yellow = 2'b10;
    parameter green = 2'b11;

    initial begin
        state <= 2'b00;
    end

    always @(posedge clk) begin
        cur_time = cur_time + 1;
        if ((state == red) & (cur_time >= r2g)) begin
            state <= green;
            cur_time <= 0;
        end else if ((state == green) & (cur_time >= g2y)) begin
            state <= yellow;
            cur_time <= 0;
        end else if ((state == yellow) & (cur_time >= y2r)) begin
            state <= red;
            cur_time <= 0;
        end
    end
endmodule

interview/traffic_light/traffic_light_tb.v
`timescale 1ns/1ns
`include "traffic_light.v"

module traffic_light_tb;
    reg clk = 1'b0;

    always #(1) clk <= ~clk;

    wire[1:0] state;

    traffic_light dut(
        .state(state),
        .clk(clk)
    );

    initial begin
        $dumpfile("traffic_light_tb.vcd");
        $dumpvars(0, traffic_light_tb);

        repeat(100) @(posedge clk);
        $finish;

    end



endmodule

interview/traffic_light/traffic_light_tb.vcd
$date
	Fri Nov 03 22:20:48 2023
$end
$version
	Icarus Verilog
$end
$timescale
	1ns
$end
$scope module traffic_light_tb $end
$var wire 2 ! state [1:0] $end
$var reg 1 " clk $end
$scope module dut $end
$var wire 1 " clk $end
$var parameter 32 # g2y $end
$var parameter 2 $ green $end
$var parameter 32 % r2g $end
$var parameter 2 & red $end
$var parameter 32 ' y2r $end
$var parameter 2 ( yellow $end
$var reg 4 ) cur_time [3:0] $end
$var reg 2 * state [1:0] $end
$upscope $end
$upscope $end
$enddefinitions $end
$comment Show the parameter values. $end
$dumpall
b10 (
b100 '
b0 &
b111 %
b11 $
b1010 #
$end
#0
$dumpvars
b0 *
b0 )
0"
b0 !
$end
#1
b1 )
1"
#2
0"
#3
b10 )
1"
#4
0"
#5
b11 )
1"
#6
0"
#7
b100 )
1"
#8
0"
#9
b101 )
1"
#10
0"
#11
b110 )
1"
#12
0"
#13
b11 !
b11 *
b0 )
1"
#14
0"
#15
b1 )
1"
#16
0"
#17
b10 )
1"
#18
0"
#19
b11 )
1"
#20
0"
#21
b100 )
1"
#22
0"
#23
b101 )
1"
#24
0"
#25
b110 )
1"
#26
0"
#27
b111 )
1"
#28
0"
#29
b1000 )
1"
#30
0"
#31
b1001 )
1"
#32
0"
#33
b10 !
b10 *
b0 )
1"
#34
0"
#35
b1 )
1"
#36
0"
#37
b10 )
1"
#38
0"
#39
b11 )
1"
#40
0"
#41
b0 !
b0 *
b0 )
1"
#42
0"
#43
b1 )
1"
#44
0"
#45
b10 )
1"
#46
0"
#47
b11 )
1"
#48
0"
#49
b100 )
1"
#50
0"
#51
b101 )
1"
#52
0"
#53
b110 )
1"
#54
0"
#55
b11 !
b11 *
b0 )
1"
#56
0"
#57
b1 )
1"
#58
0"
#59
b10 )
1"
#60
0"
#61
b11 )
1"
#62
0"
#63
b100 )
1"
#64
0"
#65
b101 )
1"
#66
0"
#67
b110 )
1"
#68
0"
#69
b111 )
1"
#70
0"
#71
b1000 )
1"
#72
0"
#73
b1001 )
1"
#74
0"
#75
b10 !
b10 *
b0 )
1"
#76
0"
#77
b1 )
1"
#78
0"
#79
b10 )
1"
#80
0"
#81
b11 )
1"
#82
0"
#83
b0 !
b0 *
b0 )
1"
#84
0"
#85
b1 )
1"
#86
0"
#87
b10 )
1"
#88
0"
#89
b11 )
1"
#90
0"
#91
b100 )
1"
#92
0"
#93
b101 )
1"
#94
0"
#95
b110 )
1"
#96
0"
#97
b11 !
b11 *
b0 )
1"
#98
0"
#99
b1 )
1"
#100
0"
#101
b10 )
1"
#102
0"
#103
b11 )
1"
#104
0"
#105
b100 )
1"
#106
0"
#107
b101 )
1"
#108
0"
#109
b110 )
1"
#110
0"
#111
b111 )
1"
#112
0"
#113
b1000 )
1"
#114
0"
#115
b1001 )
1"
#116
0"
#117
b10 !
b10 *
b0 )
1"
#118
0"
#119
b1 )
1"
#120
0"
#121
b10 )
1"
#122
0"
#123
b11 )
1"
#124
0"
#125
b0 !
b0 *
b0 )
1"
#126
0"
#127
b1 )
1"
#128
0"
#129
b10 )
1"
#130
0"
#131
b11 )
1"
#132
0"
#133
b100 )
1"
#134
0"
#135
b101 )
1"
#136
0"
#137
b110 )
1"
#138
0"
#139
b11 !
b11 *
b0 )
1"
#140
0"
#141
b1 )
1"
#142
0"
#143
b10 )
1"
#144
0"
#145
b11 )
1"
#146
0"
#147
b100 )
1"
#148
0"
#149
b101 )
1"
#150
0"
#151
b110 )
1"
#152
0"
#153
b111 )
1"
#154
0"
#155
b1000 )
1"
#156
0"
#157
b1001 )
1"
#158
0"
#159
b10 !
b10 *
b0 )
1"
#160
0"
#161
b1 )
1"
#162
0"
#163
b10 )
1"
#164
0"
#165
b11 )
1"
#166
0"
#167
b0 !
b0 *
b0 )
1"
#168
0"
#169
b1 )
1"
#170
0"
#171
b10 )
1"
#172
0"
#173
b11 )
1"
#174
0"
#175
b100 )
1"
#176
0"
#177
b101 )
1"
#178
0"
#179
b110 )
1"
#180
0"
#181
b11 !
b11 *
b0 )
1"
#182
0"
#183
b1 )
1"
#184
0"
#185
b10 )
1"
#186
0"
#187
b11 )
1"
#188
0"
#189
b100 )
1"
#190
0"
#191
b101 )
1"
#192
0"
#193
b110 )
1"
#194
0"
#195
b111 )
1"
#196
0"
#197
b1000 )
1"
#198
0"
#199
b1001 )
1"
