interview/counter/counter.v
module counter #(parameter W = 4) (
    output reg[W-1:0] count,
    
    input[W-1:0] load,
    input clk, reset, ce, le
);

    always @(posedge clk, reset) begin
        if (reset) count <= {W{1'b0}};
        else if (le) count <= load;
        else if (ce) count <= count + 1;
    end
endmodule

interview/counter/counter_tb.v
`timescale 1ns/1ps
`include "counter.v"
`ifndef W
    `define W 8
`endif
`ifndef PERIOD
    `define PERIOD 2.5
`endif

module counter_tb;
    wire[`W-1:0] count;
    reg[`W-1:0] load = {`W{1'b1}};

    reg reset=1'b0, clk=1'b0, ce=1'b0, le=1'b0;

    always #(`PERIOD/2.0) clk <= ~clk;

    counter #(.W(`W)) dut(
        .count(count),
        .load(load),
        .reset(reset),
        .clk(clk),
        .le(le),
        .ce(ce)
    );

    initial begin
        $dumpfile("counter_tb.vcd");
        $dumpvars(0, counter_tb);

        @(posedge clk);
        #0.4;

        reset = 1'b1;
        repeat (3) @(posedge clk);
        reset = 1'b0;

        @(negedge clk);
        load = `W'd13;
        le = 1'b1;
        @(negedge clk);
        le = 1'b0;
        load = `W'd2;
        repeat (2) @(posedge clk);

        @(negedge clk)
        ce = 1'b1;
        repeat(10) @(posedge clk);

        $finish;
    end
    
endmodule

interview/counter/counter_tb.vcd
$date
	Fri Nov 03 22:59:10 2023
$end
$version
	Icarus Verilog
$end
$timescale
	1ps
$end
$scope module counter_tb $end
$var wire 8 ! count [7:0] $end
$var reg 1 " ce $end
$var reg 1 # clk $end
$var reg 1 $ le $end
$var reg 8 % load [7:0] $end
$var reg 1 & reset $end
$scope module dut $end
$var wire 1 " ce $end
$var wire 1 # clk $end
$var wire 1 $ le $end
$var wire 8 ' load [7:0] $end
$var wire 1 & reset $end
$var parameter 32 ( W $end
$var reg 8 ) count [7:0] $end
$upscope $end
$upscope $end
$enddefinitions $end
$comment Show the parameter values. $end
$dumpall
b1000 (
$end
#0
$dumpvars
bx )
b11111111 '
0&
b11111111 %
0$
0#
0"
bx !
$end
#1250
1#
#1650
b0 !
b0 )
1&
#2500
0#
#3750
1#
#5000
0#
#6250
1#
#7500
0#
#8750
0&
1#
#10000
1$
b1101 %
b1101 '
0#
#11250
b1101 !
b1101 )
1#
#12500
b10 %
b10 '
0$
0#
#13750
1#
#15000
0#
#16250
1#
#17500
1"
0#
#18750
b1110 !
b1110 )
1#
#20000
0#
#21250
b1111 !
b1111 )
1#
#22500
0#
#23750
b10000 !
b10000 )
1#
#25000
0#
#26250
b10001 !
b10001 )
1#
#27500
0#
#28750
b10010 !
b10010 )
1#
#30000
0#
#31250
b10011 !
b10011 )
1#
#32500
0#
#33750
b10100 !
b10100 )
1#
#35000
0#
#36250
b10101 !
b10101 )
1#
#37500
0#
#38750
b10110 !
b10110 )
1#
#40000
0#
#41250
b10111 !
b10111 )
1#
